{
  "id": 14,
  "name_cn": "阿塔兰忒",
  "name_jp": "アタランテ",
  "name_en": "Atalanta",
  "basic": {
    "稀有度": "4",
    "获取途径": "常驻",
    "序号": "14",
    "从者内部id": "200500",
    "中文名": "阿塔兰忒",
    "日文名": "アタランテ",
    "英文名": "Atalanta",
    "中文战斗名": "阿塔兰忒",
    "日文战斗名": "アタランテ",
    "中文卡面名": "阿塔兰忒",
    "日文卡面名": "アタランテ",
    "英文卡面名": "Atalanta",
    "声优": "早见沙织",
    "画师": "RIN KUSUSAGA",
    "属性1": "中立",
    "属性2": "恶",
    "性别": "女性",
    "身高": "166cm",
    "体重": "57kg",
    "副属性": "地",
    "职阶": "Archer",
    "筋力": "D",
    "耐久": "E",
    "敏捷": "A",
    "魔力": "B",
    "幸运": "C",
    "宝具": "C",
    "基础ATK": "1438",
    "基础HP": "1996",
    "满级ATK": "8633",
    "满级HP": "12476",
    "90级ATK": "9539",
    "90级HP": "13796",
    "100级ATK": "10453",
    "100级HP": "15127",
    "第一张卡": "Quick",
    "第二张卡": "Quick",
    "第三张卡": "Arts",
    "第四张卡": "Arts",
    "第五张卡": "Buster",
    "Q卡np率": "0.50%",
    "A卡np率": "0.50%",
    "B卡np率": "0.50%",
    "EX卡np率": "0.50%",
    "宝具np率": "0.50%",
    "受击np率": "3%",
    "Q卡hit数": "3",
    "A卡hit数": "2",
    "B卡hit数": "1",
    "EX卡hit数": "3",
    "宝具卡hit数": "10",
    "Q卡伤害分布": "16,33,51",
    "A卡伤害分布": "33,67",
    "B卡伤害分布": "100",
    "EX卡伤害分布": "12,25,63",
    "宝具卡伤害分布": "3,5,3,7,8,10,12,14,16,22",
    "出星率": "8.0%",
    "即死率": "31.5%",
    "暴击权重": "148",
    "特性1": "天地从者",
    "特性2": "阿耳戈船相关人员",
    "特性3": "人科",
    "特性4": "兽科",
    "人型": "是",
    "被EA特攻": "是",
    "昵称": "阿塔,塔喵,猫茶",
    "立绘1": "第１阶段",
    "文件1": "阿塔兰忒-卡面-1",
    "立绘2": "第２阶段",
    "文件2": "阿塔兰忒-卡面-2",
    "立绘3": "第３阶段",
    "文件3": "阿塔兰忒-卡面-3",
    "立绘4": "第４阶段",
    "文件4": "阿塔兰忒-卡面-4"
  },
  "noble_phantasms": [
    {
      "中文名": "诉状箭书",
      "国服上标": "Phoebus Catastrophe",
      "日文名": "訴状の矢文",
      "日服上标": "ポイボス・カタストロフェ",
      "卡色": "Quick",
      "类型": "全体",
      "阶级": "B",
      "种类": "对军宝具",
      "效果A": "对敌方全体发动强大的攻击",
      "数值A1": "600%|数值A2=800%|数值A3=900%|数值A4=950%|数值A5=1000%",
      "效果B": "获得暴击星",
      "数值B1": "10|数值B2=15|数值B3=20|数值B4=25|数值B5=30",
      "effect_table_效果A": {
        "label": "对敌方全体发动强大的攻击",
        "levels": [
          "600%|数值A2=800%|数值A3=900%|数值A4=950%|数值A5=1000%"
        ],
        "oc_based": false,
        "np_based": false
      },
      "effect_table_效果B": {
        "label": "获得暴击星",
        "levels": [
          "10|数值B2=15|数值B3=20|数值B4=25|数值B5=30"
        ],
        "oc_based": false,
        "np_based": false
      }
    },
    {
      "中文名": "诉状箭书",
      "国服上标": "Phoebus Catastrophe",
      "日文名": "訴状の矢文",
      "日服上标": "ポイボス・カタストロフェ",
      "卡色": "Quick",
      "类型": "全体",
      "阶级": "B+",
      "种类": "对军宝具",
      "效果A": "对敌方全体发动强大的攻击",
      "数值A1": "800%|数值A2=1000%|数值A3=1100%|数值A4=1150%|数值A5=1200%",
      "效果B": "获得暴击星",
      "数值B1": "15|数值B2=20|数值B3=25|数值B4=30|数值B5=35",
      "effect_table_效果A": {
        "label": "对敌方全体发动强大的攻击",
        "levels": [
          "800%|数值A2=1000%|数值A3=1100%|数值A4=1150%|数值A5=1200%"
        ],
        "oc_based": false,
        "np_based": false
      },
      "effect_table_效果B": {
        "label": "获得暴击星",
        "levels": [
          "15|数值B2=20|数值B3=25|数值B4=30|数值B5=35"
        ],
        "oc_based": false,
        "np_based": false
      }
    }
  ],
  "active_skills": [
    {
      "icon": "绿放",
      "name_cn": "越过阿卡迪亚 B",
      "name_jp": "アルカディア越え B",
      "cooldown": "7",
      "effects": [
        "己方全体的Quick指令卡性能提升(1回合)|18%|19.8%|21.6%|23.4%|25.2%|27%|28.8%|30.6%|32.4%|36%"
      ],
      "params": {},
      "effect_tables": [
        {
          "effect": "己方全体的Quick指令卡性能提升(1回合)",
          "has_table": true,
          "levels": [
            "18%",
            "19.8%",
            "21.6%",
            "23.4%",
            "25.2%",
            "27%",
            "28.8%",
            "30.6%",
            "32.4%",
            "36%"
          ]
        }
      ]
    },
    {
      "icon": "绿放",
      "name_cn": "越过阿卡迪亚 A",
      "name_jp": "アルカディア越え A",
      "cooldown": "7",
      "effects": [
        "己方全体的Quick指令卡性能提升(1回合)|30%|32%|34%|36%|38%|40%|42%|44%|46%|50%"
      ],
      "params": {},
      "effect_tables": [
        {
          "effect": "己方全体的Quick指令卡性能提升(1回合)",
          "has_table": true,
          "levels": [
            "30%",
            "32%",
            "34%",
            "36%",
            "38%",
            "40%",
            "42%",
            "44%",
            "46%",
            "50%"
          ]
        }
      ]
    },
    {
      "icon": "集星",
      "name_cn": "逐追的美学 C",
      "name_jp": "追い込みの美学 C",
      "cooldown": "6",
      "effects": [
        "自身的暴击星集中度大幅提升(1回合)|500%|550%|600%|650%|700%|750%|800%|850%|900%|1000%"
      ],
      "params": {},
      "effect_tables": [
        {
          "effect": "自身的暴击星集中度大幅提升(1回合)",
          "has_table": true,
          "levels": [
            "500%",
            "550%",
            "600%",
            "650%",
            "700%",
            "750%",
            "800%",
            "850%",
            "900%",
            "1000%"
          ]
        }
      ]
    },
    {
      "icon": "回避",
      "name_cn": "卡吕冬狩猎 A",
      "name_jp": "カリュドーン狩り A",
      "cooldown": "8",
      "effects": [
        "付与自身回避状态(1回合)|∅|||||||||",
        "NP获得量提升(3回合)|30%|32%|34%|36%|38%|40%|42%|44%|46%|50%"
      ],
      "params": {},
      "effect_tables": [
        {
          "effect": "付与自身回避状态(1回合)",
          "has_table": true,
          "levels": [
            "∅",
            "",
            "",
            "",
            "",
            "",
            "",
            "",
            "",
            ""
          ]
        },
        {
          "effect": "NP获得量提升(3回合)",
          "has_table": true,
          "levels": [
            "30%",
            "32%",
            "34%",
            "36%",
            "38%",
            "40%",
            "42%",
            "44%",
            "46%",
            "50%"
          ]
        }
      ]
    }
  ],
  "passive_skills": [
    {
      "name": "对魔力",
      "name_jp": "对魔力",
      "rank": "D",
      "effect": "自身的弱化耐性小幅提升(12.5%)"
    },
    {
      "name": "单独行动",
      "name_jp": "单独行动",
      "rank": "A",
      "effect": "自身的暴击威力提升(10%)"
    }
  ],
  "profiles": [
    {
      "详情": "希腊神话中登场的著名女猎人。\n击退卡吕冬野猪时，因射中了第一箭而闻名遐迩。\n此外，她也加入了希腊勇者齐聚一堂的阿耳戈号，\n成了他们的一员。",
      "详情日文": "ギリシャ神話に登場する高名な女狩人。カリュドーンの猪退治の際、一番に矢を射ち込んだことで名を馳せる。\nまた、ギリシャ中の勇者が揃ったというアルゴノーツのメンバーにも加わっている。",
      "资料1条件": "",
      "资料1": "身高／体重：166cm·57kg\n出处：希腊神话\n地域：希腊\n属性：中立·恶　　副属性：地　　性别：女性\n喜欢苹果和肉。",
      "资料1日文": "身長／体重：166cm・57kg\n出典：ギリシャ神話\n地域：ギリシャ\n属性：中立・悪　　副属性：地　　性別：女性\n好物はリンゴと肉。",
      "资料2条件": "",
      "资料2": "阿塔兰忒作为某个国王的女儿出生，\n然而想要男孩的父亲嫌弃阿塔兰忒，将她丢弃在森林中。\n可怜她的女神阿耳忒弥斯用母熊的乳汁哺乳女孩，\n抚养她长大。",
      "资料2日文": "アタランテはとある国の王の娘として生まれたが、男子を欲していた父親はアタランテを疎み、森へ捨ててしまった。\nそれを哀れに思った女神アルテミスは、雌熊に乳を飲ませ、彼女を育てさせた。",
      "资料3条件": "",
      "资料3": "长大了的阿塔兰忒终于成为了一名无人能及的优秀猎人，\n成就了击退卡吕冬野猪以及加入阿耳戈号等诸多冒险。\n慕名向她求婚的人们纷纷杀到，\n烦恼的阿塔兰忒决定用赛跑向求婚者们发起挑战。",
      "资料3日文": "成長したアタランテはやがて並ぶ者なき狩人となり、カリュドーンの猪退治やアルゴノーツに参加するなど、数々の冒険を成し遂げた。\nそんな彼女の下には求婚者が押し寄せ、困ったアタランテは徒競走で勝負することにした。",
      "资料4条件": "",
      "资料4": "阿塔兰忒虽然在赛跑中本没有输给任何一个男人，\n最后却屈服于一名施计借用了女神力量的卑鄙男子，\n在半强迫的情况下嫁给了那名男子。\n传说此后又因别的事由，\n导致夫妇二人被变成狮子作为惩罚，实际无从定论。",
      "资料4日文": "アタランテはあらゆる男に徒競走で負けなかったものの、女神の力を借りた男の卑劣な策に屈し、半ば強引に娶（めと）られてしまう。\nその後は罰を受けて姿を獅子に変えられたとも伝えられているが、定かではない。",
      "资料5条件": "",
      "资料5": "她所持有的爱弓——天穹之弓（Tauropolos）\n曾接受了女神阿耳忒弥斯的祝福。\n通过向阿耳忒弥斯与其兄长太阳神阿波罗献上祈祷，\n可以发动强大的对军宝具『诉状箭书』。",
      "资料5日文": "彼女の持つ弓、天穹の弓（タウロポロス）は女神アルテミスから祝福を受けた愛用の弓である。\nアルテミスと、その兄である太陽神アポロンに祈りを捧げることにより、強力な対軍宝具『訴状の矢文』が発動する。",
      "资料6条件": "通关 女神的微笑后开放",
      "资料6": "在本作中，\n由于事关她长久以来的愿望「拯救所有的孩子」，\n因此她会积极协助你吧。\n你也应该偶尔用苹果派讨她欢心才行。",
      "资料6日文": "本作においては、兼ねてからの願いである「全ての子供を救う」というものにも関わってくるため、積極的に協力するだろう。\n君もたまにはアップルパイで彼女のご機嫌でも取ってみよう。"
    }
  ],
  "append_skills": "技能id1=3001000|技能id2=3002000|技能id3=3009000",
  "avatar_url": "",
  "card_files": [
    "阿塔兰忒-卡面-1",
    "阿塔兰忒-卡面-2",
    "阿塔兰忒-卡面-3",
    "阿塔兰忒-卡面-4"
  ],
  "card_images": [
    {
      "index": 1,
      "wiki": "阿塔兰忒-卡面-1",
      "path": "cards/14/阿塔兰忒-卡面-1.png",
      "url": "https://media.fgo.wiki/1/10/%E9%98%BF%E5%A1%94%E5%85%B0%E5%BF%92-%E5%8D%A1%E9%9D%A2-1.png"
    },
    {
      "index": 2,
      "wiki": "阿塔兰忒-卡面-2",
      "path": "cards/14/阿塔兰忒-卡面-2.png",
      "url": "https://media.fgo.wiki/c/cc/%E9%98%BF%E5%A1%94%E5%85%B0%E5%BF%92-%E5%8D%A1%E9%9D%A2-2.png"
    },
    {
      "index": 3,
      "wiki": "阿塔兰忒-卡面-3",
      "path": "cards/14/阿塔兰忒-卡面-3.png",
      "url": "https://media.fgo.wiki/1/15/%E9%98%BF%E5%A1%94%E5%85%B0%E5%BF%92-%E5%8D%A1%E9%9D%A2-3.png"
    },
    {
      "index": 4,
      "wiki": "阿塔兰忒-卡面-4",
      "path": "cards/14/阿塔兰忒-卡面-4.png",
      "url": "https://media.fgo.wiki/4/41/%E9%98%BF%E5%A1%94%E5%85%B0%E5%BF%92-%E5%8D%A1%E9%9D%A2-4.png"
    }
  ],
  "card_image_count": 4,
  "trait_list": [
    "天地从者",
    "阿耳戈船相关人员",
    "人科",
    "兽科"
  ]
}